Neuronn/Decision_Tree.py
Neuronn/Decision_Tree_Reg.py
Neuronn/KNN.py
Neuronn/Random_forest.py
Neuronn/SVM.py
Neuronn/XGBoost.py
Neuronn/__init__.py
Neuronn/linear_regression.py
Neuronn/logistic_regression.py
Neuronn/multiple_regression.py
tests/__init__.py
tests/test_Decision_Tree.py
tests/test_KNN.py
tests/test_Random_forest.py
tests/test_SVM.py
tests/test_XGBoost.py
tests/test_linear_regression.py
tests/test_multiple_regression.py
Neuronn-0.1.0.dist-info/LICENSE
Neuronn-0.1.0.dist-info/METADATA
Neuronn-0.1.0.dist-info/WHEEL
Neuronn-0.1.0.dist-info/top_level.txt
Neuronn-0.1.0.dist-info/RECORD
