Metadata-Version: 2.2
Name: Neuronn
Version: 0.1.0
Summary: A custum Python ML package
Home-page: https://github.com/username/neuron
Author: Karthikeyan
Author-email: karthikkrishna0907@gmail.com
Classifier: Programming Language :: Python :: 3
Classifier: License :: OSI Approved :: MIT License
Classifier: Operating System :: OS Independent
Requires-Python: >=3.6
License-File: LICENSE
Dynamic: author
Dynamic: author-email
Dynamic: classifier
Dynamic: description
Dynamic: description-content-type
Dynamic: home-page
Dynamic: requires-python
Dynamic: summary
